currency_converter_devworld/__init__.py
currency_converter_devworld/valiutu_konvertavimas.py
currency_converter_devworld-0.1.0.dist-info/METADATA
currency_converter_devworld-0.1.0.dist-info/WHEEL
currency_converter_devworld-0.1.0.dist-info/top_level.txt
currency_converter_devworld-0.1.0.dist-info/RECORD
